chrononav/__init__.py
chrononav/main.py
chrononav-0.1.1.dist-info/METADATA
chrononav-0.1.1.dist-info/WHEEL
chrononav-0.1.1.dist-info/entry_points.txt
chrononav-0.1.1.dist-info/top_level.txt
chrononav-0.1.1.dist-info/RECORD
