Metadata-Version: 2.4
Name: chrononav
Version: 0.1.1
Summary: A sleek CLI for timezone conversions with ASCII art and rich tables.
Home-page: https://github.com/vivek378521/chrononav
Author: Vivek Khatri
Author-email: vvk3785@gmail.com
Classifier: Programming Language :: Python :: 3
Classifier: License :: OSI Approved :: MIT License
Classifier: Operating System :: OS Independent
Classifier: Environment :: Console
Requires-Python: >=3.7
Requires-Dist: typer[all]>=0.9.0
Requires-Dist: rich>=13.0.0
Requires-Dist: pytz>=2022.1
Requires-Dist: pyfiglet>=0.8.post1
Requires-Dist: python-dateutil>=2.8.2
